stemmer_aze/create_words_txt.py
stemmer_aze/main.py
stemmer_aze/stemmer.py
stemmer_aze-0.1.2.dist-info/LICENSE.md
stemmer_aze-0.1.2.dist-info/METADATA
stemmer_aze-0.1.2.dist-info/WHEEL
stemmer_aze-0.1.2.dist-info/top_level.txt
stemmer_aze-0.1.2.dist-info/RECORD
